<mvc:View
  controllerName="BridgeManagement.dashboard.controller.Main"
  xmlns:mvc="sap.ui.core.mvc"
  xmlns="sap.m"
  xmlns:core="sap.ui.core"
  xmlns:layout="sap.ui.layout"
  xmlns:f="sap.f"
  displayBlock="true">

  <App id="dashboardApp">
    <Page
      id="dashboardPage"
      title="{i18n>appTitle}"
      showHeader="true"
      busy="{view>/busy}"
      class="dashboardPage">

      <headerContent>
        <Button
          icon="sap-icon://refresh"
          tooltip="{i18n>refreshTooltip}"
          press=".onRefresh"
          type="Transparent"
          class="dashboardRefreshBtn" />
        <Button
          icon="sap-icon://sys-help"
          tooltip="How to use this dashboard"
          press=".onShowHelp"
          type="Transparent" />
      </headerContent>

      <content>
        <ScrollContainer height="100%" width="100%" vertical="true" horizontal="false">
          <VBox class="dashboardShell">

            <!-- Summary subtitle -->
            <Text text="{i18n>pageSubtitle}" class="dashboardSubtitle sapUiSmallMarginBottom" />

            <!-- ═══ ROW 1 · Network Summary KPIs ═══ -->
            <Title text="{i18n>sectionSummary}" level="H4" class="dashboardSectionTitle" />
            <FlexBox wrap="Wrap" class="sapUiSmallMarginBottom">

              <VBox class="sapUiTinyMarginEnd sapUiTinyMarginBottom">
                <GenericTile
                  header="{i18n>kpiTotalAssets}"
                  subheader="{i18n>kpiTotalAssetsSubtitle}"
                  frameType="OneByOne"
                  press=".onNavigateBridges"
                  class="dashboardKpiTile">
                  <tileContent>
                    <TileContent>
                      <content>
                        <NumericContent
                          value="{view>/totalBridges}"
                          icon="sap-icon://functional-location"
                          valueColor="Neutral"
                          withMargin="false" />
                      </content>
                    </TileContent>
                  </tileContent>
                </GenericTile>
                <Button icon="sap-icon://sys-help" tooltip="About: Total Assets" type="Transparent"
                  press=".onTileInfo" class="sapUiTinyMarginTop">
                  <customData><core:CustomData key="tileKey" value="totalAssets"/></customData>
                </Button>
              </VBox>

              <VBox class="sapUiTinyMarginEnd sapUiTinyMarginBottom">
                <GenericTile
                  header="{i18n>kpiActiveRestrictions}"
                  subheader="{i18n>kpiActiveRestrictionsSubtitle}"
                  frameType="OneByOne"
                  press=".onNavigateRestrictions"
                  class="dashboardKpiTile">
                  <tileContent>
                    <TileContent>
                      <content>
                        <NumericContent
                          value="{view>/activeRestrictions}"
                          icon="sap-icon://alert"
                          valueColor="{= ${view>/activeRestrictions} > 0 ? 'Critical' : 'Neutral' }"
                          withMargin="false" />
                      </content>
                    </TileContent>
                  </tileContent>
                </GenericTile>
                <Button icon="sap-icon://sys-help" tooltip="About: Active Restrictions" type="Transparent"
                  press=".onTileInfo" class="sapUiTinyMarginTop">
                  <customData><core:CustomData key="tileKey" value="activeRestrictions"/></customData>
                </Button>
              </VBox>

              <VBox class="sapUiTinyMarginEnd sapUiTinyMarginBottom">
                <GenericTile
                  header="{i18n>kpiBridgesClosed}"
                  subheader="{i18n>kpiBridgesClosedSubtitle}"
                  frameType="OneByOne"
                  press=".onNavigateClosedBridges"
                  class="dashboardKpiTile">
                  <tileContent>
                    <TileContent>
                      <content>
                        <NumericContent
                          value="{view>/closedBridges}"
                          icon="sap-icon://locked"
                          valueColor="{= ${view>/closedBridges} > 0 ? 'Critical' : 'Good' }"
                          withMargin="false" />
                      </content>
                    </TileContent>
                  </tileContent>
                </GenericTile>
                <Button icon="sap-icon://sys-help" tooltip="About: Bridges Closed" type="Transparent"
                  press=".onTileInfo" class="sapUiTinyMarginTop">
                  <customData><core:CustomData key="tileKey" value="bridgesClosed"/></customData>
                </Button>
              </VBox>

            </FlexBox>

            <!-- ═══ ROW 2 · Condition State Distribution ═══ -->
            <Title text="{i18n>sectionCondition}" level="H4" class="dashboardSectionTitle" />
            <VBox class="dashboardCard sapUiSmallMarginBottom">

              <!-- Card header row -->
              <HBox justifyContent="SpaceBetween" alignItems="Center" class="dashboardCardHeader">
                <HBox alignItems="Center">
                  <core:Icon src="sap-icon://status-positive" class="dashboardConditionHeaderIcon sapUiTinyMarginEnd" />
                  <Text text="{view>/conditionSummaryLabel}" class="dashboardConditionSummary" />
                </HBox>
                <Text text="{view>/totalBridges} {i18n>bridgesLabel}" class="dashboardMuted" />
              </HBox>

              <!-- Condition rows -->
              <VBox class="dashboardConditionRows">
                <List
                  items="{view>/conditionRows}"
                  showSeparators="None"
                  class="dashboardConditionList">
                  <items>
                    <CustomListItem class="dashboardConditionItem">
                      <HBox alignItems="Center" class="dashboardConditionRow">
                        <core:Icon src="{view>icon}" color="{view>color}" size="1rem" class="dashboardConditionIcon" />
                        <Text text="{view>label}" width="5.5rem" class="dashboardConditionLabel" />
                        <ProgressIndicator
                          percentValue="{view>pct}"
                          displayValue="{view>pctText}"
                          state="{view>state}"
                          showValue="true"
                          width="100%"
                          class="dashboardConditionBar">
                          <layoutData>
                            <FlexItemData growFactor="1" shrinkFactor="1" minWidth="0px" />
                          </layoutData>
                        </ProgressIndicator>
                        <Text text="{view>pct}% · {view>count}" class="dashboardConditionCount" />
                      </HBox>
                    </CustomListItem>
                  </items>
                </List>
              </VBox>

            </VBox>

            <!-- ═══ ROW 3 · Key Indicators ═══ -->
            <Title text="{i18n>sectionKeyIndicators}" level="H4" class="dashboardSectionTitle" />
            <FlexBox wrap="Wrap" class="sapUiSmallMarginBottom">

              <VBox class="dashboardIndicatorCard sapUiTinyMarginEnd sapUiTinyMarginBottom">
                <HBox justifyContent="SpaceBetween" alignItems="Center">
                  <Text text="{i18n>indicatorSufficiency}" class="dashboardIndicatorLabel" />
                  <Button icon="sap-icon://sys-help" tooltip="About: Sufficiency Rating" type="Transparent" press=".onTileInfo">
                    <customData><core:CustomData key="tileKey" value="sufficiency"/></customData>
                  </Button>
                </HBox>
                <HBox alignItems="Baseline">
                  <Text text="{view>/sufficiencyPct}" class="dashboardIndicatorValue" />
                  <Text text="%" class="dashboardIndicatorUnit" />
                </HBox>
                <Text text="{i18n>indicatorSufficiencyHint}" class="dashboardMuted" />
              </VBox>

              <VBox class="dashboardIndicatorCard sapUiTinyMarginEnd sapUiTinyMarginBottom">
                <HBox justifyContent="SpaceBetween" alignItems="Center">
                  <Text text="{i18n>indicatorScourCritical}" class="dashboardIndicatorLabel" />
                  <Button icon="sap-icon://sys-help" tooltip="About: Scour Critical Bridges" type="Transparent" press=".onTileInfo">
                    <customData><core:CustomData key="tileKey" value="scourCritical"/></customData>
                  </Button>
                </HBox>
                <HBox alignItems="Baseline">
                  <Text text="{view>/scourCritical}" class="{= ${view>/scourCritical} > 0 ? 'dashboardIndicatorValueCritical' : 'dashboardIndicatorValue' }" />
                </HBox>
                <Text text="{i18n>indicatorScourCriticalHint}" class="dashboardMuted" />
              </VBox>

              <VBox class="dashboardIndicatorCard sapUiTinyMarginEnd sapUiTinyMarginBottom">
                <HBox justifyContent="SpaceBetween" alignItems="Center">
                  <Text text="{i18n>indicatorDeficient}" class="dashboardIndicatorLabel" />
                  <Button icon="sap-icon://sys-help" tooltip="About: Structurally Deficient" type="Transparent" press=".onTileInfo">
                    <customData><core:CustomData key="tileKey" value="deficient"/></customData>
                  </Button>
                </HBox>
                <HBox alignItems="Baseline">
                  <Text text="{view>/deficient}" class="{= ${view>/deficient} > 0 ? 'dashboardIndicatorValueCritical' : 'dashboardIndicatorValue' }" />
                </HBox>
                <Text text="{i18n>indicatorDeficientHint}" class="dashboardMuted" />
              </VBox>

            </FlexBox>

            <!-- ═══ ROW 4 · Active Restrictions Detail ═══ -->
            <Title text="{i18n>sectionActiveRestrictions}" level="H4" class="dashboardSectionTitle" />
            <VBox class="dashboardCard sapUiSmallMarginBottom">
              <HBox class="dashboardCardHeader" alignItems="Center" justifyContent="SpaceBetween">
                <HBox alignItems="Center">
                  <core:Icon src="sap-icon://warning2" color="#E76500" size="1rem" class="sapUiTinyMarginEnd" />
                  <Text text="{i18n>postedRestrictionsLabel}" class="dashboardBodyText" />
                </HBox>
                <ObjectNumber
                  number="{view>/postedRestrictions}"
                  unit="{i18n>postedRestrictionsUnit}"
                  state="{= ${view>/postedRestrictions} > 0 ? 'Warning' : 'None' }"
                  emphasized="false" />
              </HBox>
            </VBox>

            <!-- ═══ ROW 5 · Quick Navigation ═══ -->
            <Title text="Quick Navigation" level="H4" class="dashboardSectionTitle" />
            <FlexBox wrap="Wrap" class="sapUiSmallMarginBottom dashboardQuickNav">
              <Button text="Bridge Register" icon="sap-icon://functional-location" press=".onNavigateBridges"
                type="Emphasized" class="sapUiTinyMarginEnd sapUiTinyMarginBottom" />
              <Button text="Restrictions" icon="sap-icon://alert" press=".onNavigateRestrictions"
                type="Emphasized" class="sapUiTinyMarginEnd sapUiTinyMarginBottom" />
              <Button text="Map View" icon="sap-icon://map" press=".onNavigateMap"
                type="Emphasized" class="sapUiTinyMarginEnd sapUiTinyMarginBottom" />
              <Button text="Mass Edit" icon="sap-icon://edit" press=".onNavigateMassEdit"
                type="Default" class="sapUiTinyMarginEnd sapUiTinyMarginBottom" />
            </FlexBox>

            <!-- Last refreshed -->
            <HBox justifyContent="End" class="sapUiSmallMarginBottom">
              <Text text="{view>/lastRefreshedLabel}" class="dashboardMuted" />
            </HBox>

          </VBox>
        </ScrollContainer>
      </content>

    </Page>
  </App>
</mvc:View>
